httpx_socks/__init__.py
httpx_socks/_async_proxy.py
httpx_socks/_async_transport.py
httpx_socks/_sync_proxy.py
httpx_socks/_sync_stream.py
httpx_socks/_sync_transport.py
httpx_socks-0.9.1.dist-info/LICENSE.txt
httpx_socks-0.9.1.dist-info/METADATA
httpx_socks-0.9.1.dist-info/WHEEL
httpx_socks-0.9.1.dist-info/top_level.txt
httpx_socks-0.9.1.dist-info/RECORD
