Metadata-Version: 2.1
Name: httpx-socks
Version: 0.9.1
Summary: Proxy (HTTP, SOCKS) transports for httpx
Home-page: https://github.com/romis2012/httpx-socks
Author: Roman Snegirev
Author-email: snegiryev@gmail.com
License: Apache 2
Keywords: httpx asyncio socks socks5 socks4 http proxy
License-File: LICENSE.txt
Requires-Dist: httpx <0.28.0,>=0.21.0
Requires-Dist: httpcore <2.0,>=0.17.3
Requires-Dist: python-socks >=2.0.0
Provides-Extra: asyncio
Requires-Dist: async-timeout >=3.0.1 ; extra == 'asyncio'
Provides-Extra: trio
Requires-Dist: trio >=0.16.0 ; extra == 'trio'
